{
  "chunk_id": "DOC-000132",
  "root_file": "CustomerWebUserGuide.adoc",
  "heading_path": [
    {
      "level": 1,
      "title": "Dokumentacja użytkownika systemu Asseco EBP :  Aplikacja WWW Klienta Firmowego"
    },
    {
      "level": 2,
      "title": "Karty (Visiona)"
    },
    {
      "level": 3,
      "title": "Spłata karty kredytowej"
    }
  ],
  "section_title": "Spłata karty kredytowej",
  "text": "Aby spłacić zadłużenie na karcie kredytowej należy kliknąć w opcję [SPŁAĆ KARTĘ] na widżecie KARTY, albo na formularzu KARTY kliknąć w obszar karty, a następnie wybrać opcję [SPŁAĆ]. Funkcjonalność spłaty nie jest dostępna dla karty debetowej.\n\nPo wyborze przycisku wyświetlony zostaje formularz SPŁATA KARTY z następującymi danymi:\n\nimage::Karty/image49.png[image,width=604,height=237]\n\n* *Rachunek karty* – pole wypełnione numerem rachunku karty, pole zablokowane do edycji,\n* *Z rachunku* – pole zawierające listę rachunków Użytkownika, należy wskazać rachunek, z którego ma być wykonana spłata zadłużenia na karcie, realizacja spłaty karty możliwa jest z rachunków w walucie PLN lub w walucie rachunku karty. W polu podpowiadany jest rachunek ustawiony przez Użytkownika jako domyślny (w opcji _Ustawienia → Rachunek domyślny_), który można zmienić, pole wymagalne,\n* *Data wymaganej spłaty* – pole wypełnione automatycznie przez system datą, do której należy uregulować zadłużenie(data w formacie DD.MM.RRRR), pole zablokowane do edycji,\n* *Typ spłaty* – wariant spłaty zadłużenia, dostępne wartości:\n\n** Kwota minimalna, wraz z informacją o minimalnej kwocie do spłaty oraz pozostałej minimalnej kwocie do spłaty,\n** Kwota dowolna,\n** Kwota całkowita, wraz z informacją o kwocie wymagalnej do całkowitej spłaty,\n** Zadłużenie za ostatni okres rozliczeniowy, wraz z informacją o kwocie zadłużenia za ostatni okres rozliczeniowy oraz kwocie pozostałej do spłaty zadłużenia za ostatni okres rozliczeniowy.\n\nimage::Karty/image50.png[image,width=313,height=223]\n\n* *Kwota* – kwota spłaty zadłużenia w walucie rachunku karty (kwota nie może być większa od kwoty całkowitego zadłużenia na karcie). Pole kwota:\n\n** należy uzupełnić ręcznie w przypadku wybrania typu spłaty:\n\n*** Kwota dowolna,\n\n** pole wypełniane automatycznie (bez możliwości zmiany) w przypadku wskazania typu spłaty:\n\n*** Kwota minimalna,\n*** Kwota całkowita,\n*** Zadłużenie za ostatni okres rozliczeniowy,\n\n* *Tytułem* – pole zawiera opis operacji i zaszyfrowany numer karty, pole zablokowane do edycji, informacja jaką system zaprezentuje w tym polu, jest uzależniony od wybranego przez Użytkownika typu spłaty:\n\n** Minimalna kwota – Spłata minimalnego zadł. karty nr (numer karty np. 4774 xxxx xxxx 0003),\n** Kwota całkowita - Spłata całkowitego zadł. karty nr (numer karty np. 4774 xxxx xxxx 0003),\n** Zadłużenie za ostatni okres rozliczeniowy - Spłata ostatnie zadł. karty nr (numer karty np. 4774 xxxx xxxx 0003),\n\n* *Data realizacji* – data spłaty zadłużenia (data w formacie DD.MM.RRRR), domyślnie wstawiana jest data bieżąca, pole zablokowane do edycji.\n\nW górnej część formularza SPŁATA KARTY dostępne są przyciski:\n\n* image:Karty/image36.png[image,width=45,height=53] umożliwiający powrót do formularza KARTY.\n* image:Karty/image37.png[image,width=48,height=61]– umożliwiający przejście do pulpitu.\n\nPo określeniu parametrów spłaty karty kredytowej należy nacisnąć przycisk [SPŁAĆ], system wyświetla wówczas formularz z wprowadzonymi danymi w trybie podglądu.\n\nimage::Karty/image51.png[image,width=603,height=205]\n\nNa formularzu prezentowane są następujące informacje:\n\n* *Rachunek karty* – numer rachunku karty,\n* *Z rachunku* – numer rachunku z którego będzie wykonywana spłata,\n* *Kwota* – kwota spłaty,\n* *Tytułem* – pole automatyczne uzupełnianie przez system,\n* *Data realizacji* – data realizacji spłaty,\n* *Podaj kod autoryzacyjny/Klucz do podpisu* – jedno aktywne pole na formatce, służące do autoryzacji przelewu. Nazwa i prezentacja pola zależna jest od aktualnie wykorzystywanej przez Użytkownika metody autoryzacji.\n\nDodatkowo na formularzu prezentowana jest rozwijana sekcja:\n\n* [POKAŻ DODATKOWE INFORMACJE]:\n\n** *Data dostarczenia* – data wykonania operacji,\n** *Opłaty* – kwota opłaty związanej z wykonaniem operacji spłaty,\n\nimage::Karty/image52.png[image,width=367,height=126]\n\nW górnej części formularza SPŁATA KARTY dostępny jest przycisk:\n\n* image:Karty/image36.png[image,width=45,height=53] – umożliwiający powrót do formularza pierwszego kroku SPŁATA KARTY,\n\nPo zaakceptowaniu operacji spłaty karty kredytowej za pomocą dostępnej metody autoryzacji, zostanie zaprezentowany komunikat jak na poniższym ekranie wraz z przyciskiem [WRÓĆ DO PULPITU] umożliwiającym powrót do pulpitu.\n\nimage::Karty/image53.png[image,width=534,height=339]\n",
  "primary_source_file": "miniapps/Miniaplikacja_Karty.adoc",
  "provenance": [
    {
      "source_file": "miniapps/Miniaplikacja_Karty.adoc",
      "line_start": 487,
      "line_end": 560
    }
  ]
}